lib/__init__.py
lib/utils.py
helloadarshhme-0.0.1.dist-info/METADATA
helloadarshhme-0.0.1.dist-info/WHEEL
helloadarshhme-0.0.1.dist-info/top_level.txt
helloadarshhme-0.0.1.dist-info/RECORD
