Metadata-Version: 2.1
Name: helloadarshhme
Version: 0.0.1
Summary: A basic hello package
Author: Adarsh Kesharwani
Author-email: <akesherwani900@gamil.com>
Keywords: python
Classifier: Development Status :: 1 - Planning
Classifier: Intended Audience :: Developers
Classifier: Programming Language :: Python :: 3
Classifier: Operating System :: Unix
Classifier: Operating System :: MacOS :: MacOS X
Classifier: Operating System :: Microsoft :: Windows
